src/__init__.py
src/main.py
src/Data/sample_df.csv
src/Data/survive.db
src/config/__init__.py
src/config/config.yml
src/config/settings.py
src/config/__pycache__/__init__.cpython-310.pyc
src/config/__pycache__/settings.cpython-310.pyc
src/model/__init__.py
src/model/log_file.txt
src/model/pipeline.pkl
src/model/pipeline.py
src/model/predict.py
src/model/train_pipeline.py
src/model/__pycache__/__init__.cpython-310.pyc
src/model/__pycache__/pipeline.cpython-310.pyc
src/model/__pycache__/predict.cpython-310.pyc
src/preprocessing/__init__.py
src/preprocessing/datamanager.py
src/preprocessing/validation.py
src/test/__init__.py
src/test/test_bound_outliers.py
src/test/test_load_from_database.py
src/test/test_pipline.py
src/test/test_predict.py
src/test/test_predict_api.py
src/test/test_predict_api_dict.py
src/test/test_preprocess_data.py
src/test/test_preprocess_input.py
heart_disease_classification_model-0.0.13.dist-info/METADATA
heart_disease_classification_model-0.0.13.dist-info/WHEEL
heart_disease_classification_model-0.0.13.dist-info/top_level.txt
heart_disease_classification_model-0.0.13.dist-info/RECORD
