Metadata-Version: 2.1
Name: heart-disease-classification-model
Version: 0.0.13
Summary: Classifying whether the patient will survive
Home-page: https://github.com/ChngYuanLongRandy/demo_deploy
Author: RandyChng
Author-email: chngyuanlong@gmail.com
License: BSD-3
Platform: UNKNOWN
Classifier: License :: OSI Approved :: MIT License
Classifier: Programming Language :: Python :: 3.10
Requires-Python: ==3.10.0
Requires-Dist: numpy
Requires-Dist: pandas
Requires-Dist: pydantic
Requires-Dist: scikit-learn
Requires-Dist: strictyaml
Requires-Dist: joblib
